topsis/__init__.py
topsis/topsis.py
topsis_rishabhsharma_102303286-1.0.dist-info/METADATA
topsis_rishabhsharma_102303286-1.0.dist-info/WHEEL
topsis_rishabhsharma_102303286-1.0.dist-info/entry_points.txt
topsis_rishabhsharma_102303286-1.0.dist-info/top_level.txt
topsis_rishabhsharma_102303286-1.0.dist-info/RECORD
