Metadata-Version: 2.4
Name: Topsis-RishabhSharma-102303286
Version: 1.0
Summary: TOPSIS implementation
Author: Rishabh Sharma
Requires-Dist: pandas
Requires-Dist: numpy
Dynamic: author
Dynamic: description
Dynamic: description-content-type
Dynamic: requires-dist
Dynamic: summary
